test1.py
test2.py
nalangTest/test1.py
nalangTest/test2.py
nalangTest2/bmi.py
nalangTest2/test1.py
nalangTest2/test2.py
nalangTest2-0.0.0.3.dist-info/METADATA
nalangTest2-0.0.0.3.dist-info/WHEEL
nalangTest2-0.0.0.3.dist-info/top_level.txt
nalangTest2-0.0.0.3.dist-info/RECORD
